py_sofistik_utils/__init__.py
py_sofistik_utils/py.typed
py_sofistik_utils/cdb_reader/__init__.py
py_sofistik_utils/cdb_reader/reader.py
py_sofistik_utils/cdb_reader/_internal/__init__.py
py_sofistik_utils/cdb_reader/_internal/beam_data.py
py_sofistik_utils/cdb_reader/_internal/beam_load.py
py_sofistik_utils/cdb_reader/_internal/beam_results.py
py_sofistik_utils/cdb_reader/_internal/beam_stresses.py
py_sofistik_utils/cdb_reader/_internal/cable_data.py
py_sofistik_utils/cdb_reader/_internal/cable_load.py
py_sofistik_utils/cdb_reader/_internal/cable_results.py
py_sofistik_utils/cdb_reader/_internal/group_data.py
py_sofistik_utils/cdb_reader/_internal/group_lc_data.py
py_sofistik_utils/cdb_reader/_internal/load_cases.py
py_sofistik_utils/cdb_reader/_internal/node_data.py
py_sofistik_utils/cdb_reader/_internal/node_residuals.py
py_sofistik_utils/cdb_reader/_internal/node_results.py
py_sofistik_utils/cdb_reader/_internal/nodes.py
py_sofistik_utils/cdb_reader/_internal/plate_data.py
py_sofistik_utils/cdb_reader/_internal/property.py
py_sofistik_utils/cdb_reader/_internal/sec_group_lc_data.py
py_sofistik_utils/cdb_reader/_internal/sofistik_classes.py
py_sofistik_utils/cdb_reader/_internal/sofistik_dll.py
py_sofistik_utils/cdb_reader/_internal/sofistik_utilities.py
py_sofistik_utils/cdb_reader/_internal/spring_data.py
py_sofistik_utils/cdb_reader/_internal/spring_results.py
py_sofistik_utils/cdb_reader/_internal/sys_info.py
py_sofistik_utils/cdb_reader/_internal/truss_data.py
py_sofistik_utils/cdb_reader/_internal/truss_load.py
py_sofistik_utils/cdb_reader/_internal/truss_results.py
py_sofistik_utils-0.0.1.dist-info/licenses/LICENSE
py_sofistik_utils-0.0.1.dist-info/METADATA
py_sofistik_utils-0.0.1.dist-info/WHEEL
py_sofistik_utils-0.0.1.dist-info/top_level.txt
py_sofistik_utils-0.0.1.dist-info/RECORD
