Metadata-Version: 2.4
Name: py-sofistik-utils
Version: 0.0.1
Summary: The Studio W SOFiSTiK package
Author-email: StudioWEngineers <studio.w.engineers@gmail.com>
License-Expression: BSD-3-Clause
Classifier: Intended Audience :: Developers
Classifier: Programming Language :: Python :: 3 :: Only
Classifier: Programming Language :: Python :: 3.12
Classifier: Programming Language :: Python :: 3.13
Classifier: Programming Language :: Python :: 3.14
Classifier: Programming Language :: Python :: Implementation :: CPython
Classifier: Operating System :: Microsoft :: Windows
Classifier: Topic :: Software Development :: Libraries :: Python Modules
Classifier: Topic :: Utilities
Classifier: Typing :: Typed
Classifier: Development Status :: 4 - Beta
Requires-Python: >=3.12
License-File: LICENSE
Requires-Dist: numpy>=2.2.0
Requires-Dist: pandas>=3.0.0
Dynamic: license-file
